modesto/__init__.py
modesto/git.py
modesto/kubectl.py
modesto/systemd.py
modesto/docker/__init__.py
modesto/docker/compose.py
modesto/docker/engine.py
modesto-1.0.0.dist-info/LICENSE
modesto-1.0.0.dist-info/METADATA
modesto-1.0.0.dist-info/WHEEL
modesto-1.0.0.dist-info/entry_points.txt
modesto-1.0.0.dist-info/top_level.txt
modesto-1.0.0.dist-info/zip-safe
modesto-1.0.0.dist-info/RECORD
