Metadata-Version: 2.1
Name: modesto
Version: 1.0.0
Summary: command-line utility wrappers
Home-page: https://github.com/ecks0/modesto
Author: Nick Zigarovich
Author-email: nick@zigarovich.io
License: UNKNOWN
Platform: UNKNOWN
Requires-Python: >= 3.6
Requires-Dist: lura (>=1.0.0)
